pynumaflow/__init__.py
pynumaflow/_constants.py
pynumaflow/accumulator/__init__.py
pynumaflow/accumulator/_dtypes.py
pynumaflow/accumulator/async_server.py
pynumaflow/accumulator/servicer/__init__.py
pynumaflow/accumulator/servicer/async_servicer.py
pynumaflow/accumulator/servicer/task_manager.py
pynumaflow/batchmapper/__init__.py
pynumaflow/batchmapper/_dtypes.py
pynumaflow/batchmapper/async_server.py
pynumaflow/batchmapper/servicer/__init__.py
pynumaflow/batchmapper/servicer/async_servicer.py
pynumaflow/errors/__init__.py
pynumaflow/errors/_dtypes.py
pynumaflow/errors/errors.py
pynumaflow/exceptions.py
pynumaflow/info/__init__.py
pynumaflow/info/server.py
pynumaflow/info/types.py
pynumaflow/mapper/__init__.py
pynumaflow/mapper/_dtypes.py
pynumaflow/mapper/_servicer/__init__.py
pynumaflow/mapper/_servicer/_async_servicer.py
pynumaflow/mapper/_servicer/_sync_servicer.py
pynumaflow/mapper/async_server.py
pynumaflow/mapper/multiproc_server.py
pynumaflow/mapper/sync_server.py
pynumaflow/mapstreamer/__init__.py
pynumaflow/mapstreamer/_dtypes.py
pynumaflow/mapstreamer/async_server.py
pynumaflow/mapstreamer/servicer/__init__.py
pynumaflow/mapstreamer/servicer/async_servicer.py
pynumaflow/proto/__init__.py
pynumaflow/proto/accumulator/__init__.py
pynumaflow/proto/accumulator/accumulator.proto
pynumaflow/proto/accumulator/accumulator_pb2.py
pynumaflow/proto/accumulator/accumulator_pb2.pyi
pynumaflow/proto/accumulator/accumulator_pb2_grpc.py
pynumaflow/proto/mapper/__init__.py
pynumaflow/proto/mapper/map.proto
pynumaflow/proto/mapper/map_pb2.py
pynumaflow/proto/mapper/map_pb2.pyi
pynumaflow/proto/mapper/map_pb2_grpc.py
pynumaflow/proto/reducer/__init__.py
pynumaflow/proto/reducer/reduce.proto
pynumaflow/proto/reducer/reduce_pb2.py
pynumaflow/proto/reducer/reduce_pb2.pyi
pynumaflow/proto/reducer/reduce_pb2_grpc.py
pynumaflow/proto/sideinput/__init__.py
pynumaflow/proto/sideinput/sideinput.proto
pynumaflow/proto/sideinput/sideinput_pb2.py
pynumaflow-0.11.0.dist-info/METADATA
pynumaflow-0.11.0.dist-info/WHEEL
pynumaflow-0.11.0.dist-info/licenses/LICENSE
pynumaflow-0.11.0.dist-info/RECORD
