Metadata-Version: 2.4
Name: pynumaflow
Version: 0.11.0
Summary: Provides the interfaces of writing Python User Defined Functions and Sinks for NumaFlow.
License: Apache-2.0
License-File: LICENSE
Author: NumaFlow Developers
Maintainer: Avik Basu
Maintainer-email: avikbasu93@gmail.com
Requires-Python: >=3.9,<3.15
Classifier: Intended Audience :: Developers
Classifier: License :: OSI Approved :: Apache Software License
Classifier: Programming Language :: Python :: 3
Classifier: Programming Language :: Python :: 3.9
Classifier: Programming Language :: Python :: 3.10
Classifier: Programming Language :: Python :: 3.11
Classifier: Programming Language :: Python :: 3.12
Classifier: Programming Language :: Python :: 3.13
Classifier: Programming Language :: Python :: 3.14
Classifier: Topic :: Software Development :: Libraries
Requires-Dist: aiorun (>=2023.7,<2024.0)
Requires-Dist: google-api-core (>=2.11.0,<3.0.0)
Requires-Dist: google-cloud (>=0.34.0,<0.35.0)
Requires-Dist: grpcio (>=1.48.1,<2.0.0)
Requires-Dist: grpcio-status (>=1.48.1,<2.0.0)
Requires-Dist: grpcio-tools (>=1.48.1,<2.0.0)
Requires-Dist: protobuf (>=3.20,<7.0)
Requires-Dist: psutil (>=6.0.0,<7.0.0)
Requires-Dist: uvloop (>=0.21.0,<0.22.0)
Project-URL: Repository, https://github.com/numaproj/numaflow-python
